<?xml version="1.0" encoding="UTF-8"?>
<!DOCTYPE mapper
        PUBLIC "-//mybatis.org//DTD Mapper 3.0//EN"
        "http://mybatis.org/dtd/mybatis-3-mapper.dtd">

<mapper namespace="com.suzao.net.speed.netspeed.dao.network.ExperienceSpeedDao">

    <resultMap id="experienceSpeed" type="com.suzao.net.speed.netspeed.vo.network.ExperienceSpeedVo">
        <id column="id" property="id"></id>
        <result column="platform" property="platform"></result>
        <result column="speed" property="speed"></result>
        <result column="time" property="time"></result>
        <result column="address" property="address"></result>
        <result column="macAddress" property="macAddress"></result>
        <result column="macAddress5G" property="macAddress5G"></result>
        <result column="sceneId" property="sceneId"></result>
        <result column="areaId" property="areaId"></result>
        <result column="apId" property="apId"></result>
        <result column="apName" property="apName"></result>
        <result column="sceneName" property="sceneName"></result>
        <result column="areaName" property="areaName"></result>
        <result column="speedometer" property="speedometer"></result>

        <result column="responseState" property="responseState"></result>
        <result column="connectTime" property="connectTime"></result>
        <result column="redirectTime" property="redirectTime"></result>
        <result column="responseTime" property="responseTime"></result>
        <result column="requestTime" property="requestTime"></result>
        <result column="domainTime" property="domainTime"></result>
        <result column="webTime" property="webTime"></result>
        <result column="webSuccess" property="webSuccess"></result>
    </resultMap>

    <insert id="insert" parameterType="java.util.List">
        replace into experiencespeed
        (id,platform,speed,time,address,macAddress,macAddress5G,sceneId,areaId,apId,speedometer,responseState,connectTime,redirectTime
        ,responseTime,requestTime,domainTime,webTime,webSuccess)
        values
        <foreach collection="list" item="item" separator=",">
            (#{item.id},#{item.platform},#{item.speed},#{item.time},#{item.address},#{item.macAddress},#{item.macAddress5G},#{item.sceneId}
            ,#{item.areaId},#{item.apId},#{item.speedometer}
            ,#{item.responseState},#{item.connectTime},#{item.redirectTime},#{item.responseTime},#{item.requestTime},#{item.domainTime},#{item.webTime},#{item.webSuccess})
        </foreach>
    </insert>

    <select id="selectAll" resultMap="experienceSpeed">
        SELECT
        es.`id`,
        es.`platform`,
        es.`speed`,
        es.`time`,
        es.`address`,
        es.`macAddress`,
        es.`macAddress5G`,
        es.`sceneId`,
        es.`areaId`,
        es.`apId`,
        es.`speedometer`,
        scene.`name` sceneName,
        area.`name` areaName,
        ap.`name` apName
        FROM
        experiencespeed es
        LEFT JOIN scene
        ON es.`sceneId`=scene.`id`
        LEFT JOIN area
        ON es.`areaId`=area.`id`
        LEFT JOIN ap
        on es.`apId`=ap.`id`
        where
        1=1 and
        es.`speedometer` like CONCAT('%',#{speedometer},'%') and
        es.time <![CDATA[>= ]]> DATE_FORMAT(#{startTime},'%Y-%m-%d 00:00:00') and
        es.time <![CDATA[<= ]]> DATE_FORMAT(#{endTime},'%Y-%m-%d 23:59:59')
        <if test="sceneId!=null">
            AND es.`sceneId` LIKE CONCAT('%',#{sceneId},'%')
        </if>
        <if test="areaId!=null">
            AND es.`areaId` LIKE CONCAT('%',#{areaId},'%')
        </if>
        <if test="apId!=null">
            AND es.`apId` LIKE CONCAT('%',#{apId},'%')
        </if>
        ORDER BY es.`time` DESC
    </select>


    <select id="findById" resultType="com.suzao.net.speed.netspeed.vo.network.ExperienceSpeedVo">
        SELECT
        es.`id`,
        es.`platform`,
        es.`speed`,
        es.`time`,
        es.`address`,
        es.`macAddress`,
        es.`macAddress5G`,
        es.`sceneId`,
        es.`areaId`,
        es.`apId`,
        es.`speedometer`,
        scene.`name` sceneName,
        area.`name` areaName,
        ap.`name` apName
        FROM
        experiencespeed es
        LEFT JOIN scene
        ON es.`sceneId`=scene.`id`
        LEFT JOIN area
        ON es.`areaId`=area.`id`
        LEFT JOIN ap
        on es.`apId`=ap.`id`
        where
        es.id=#{id}
    </select>

    <select id="experiencePassvalue" resultType="com.suzao.net.speed.netspeed.vo.network.ExperienceSpeedVo"
            parameterType="java.util.List">
        SELECT scene.name sceneName,
        area.name areaName,
        ap.name apName,
        es.time,
        IFNULL((es.speed),0) speed
        FROM scene LEFT JOIN experiencespeed es ON
        es.`sceneId`=scene.`id`
        LEFT JOIN area
        ON es.`areaId`=area.`id`
        LEFT JOIN ap
        on es.`apId`=ap.`id`
        where
        1=1
        <if test="sceneId!=null">
            and scene.id=#{sceneId}
        </if>
        order by scene.id
        <!--<if test="areaId!=null">-->
        <!--AND es.`areaId` LIKE CONCAT('%',#{areaId},'%')-->
        <!--</if>-->
        <!--<if test="apId!=null">-->
        <!--AND es.`apId` LIKE CONCAT('%',#{apId},'%')-->
        <!--</if>-->
    </select>

    <select id="experiencePassvalueArea" resultType="com.suzao.net.speed.netspeed.vo.network.ExperienceSpeedVo"
            parameterType="java.util.List">
        SELECT scene.name sceneName,
        area.name areaName,
        ap.name apName,
        es.time,
        IFNULL((es.speed),0) speed
        FROM area LEFT JOIN experiencespeed es ON
        es.`areaId`=area.`id`
        LEFT JOIN scene
        ON es.`sceneId`=scene.`id`
        LEFT JOIN ap
        on es.`apId`=ap.`id`
        where
        1=1
        <if test="sceneId!=null">
            and area.sceneId=#{sceneId}
        </if>
        order by scene.id
        <!--<if test="areaId!=null">-->
        <!--/* AND es.`areaId` LIKE CONCAT('%',#{areaId},'%')*/-->
        <!--and area.sceneId=#{sceneId}-->
        <!--</if>-->
        <!--<if test="apId!=null">-->
        <!--AND es.`apId` LIKE CONCAT('%',#{apId},'%')-->
        <!--</if>-->
    </select>

    <select id="experiencePassvalueAP" resultType="com.suzao.net.speed.netspeed.vo.network.ExperienceSpeedVo"
            parameterType="java.util.List">
        SELECT scene.name sceneName,
        area.name areaName,
        ap.name apName,
        es.time,
        IFNULL((es.speed),0) speed
        FROM ap LEFT JOIN experiencespeed es ON
        es.`apId`=ap.`id`
        LEFT JOIN scene
        ON es.`sceneId`=scene.`id`
        LEFT JOIN area
        on es.`areaId`=area.`id`
        where
        1=1
        <!--<if test="sceneId!=null">-->
        <!--AND es.`sceneId` LIKE CONCAT('%',#{sceneId},'%')-->
        <!--</if>-->
        <if test="areaId!=null">
            and ap.areaId=#{areaId}
        </if>
        order by scene.id
        <!--<if test="apId!=null">-->
        <!--/*AND es.`apId` LIKE CONCAT('%',#{apId},'%')*/-->
        <!--and ap.areaId=#{areaId}-->
        <!--</if>-->
    </select>

    <select id="selectAPCountByTestFromExperienceSpeed" resultType="com.suzao.net.speed.netspeed.vo.network.PassValueVo"
            parameterType="java.util.List">
        SELECT ap.id,ap.name apName,scene.name sceneName, area.name areaName
        FROM experiencespeed es
        LEFT JOIN scene ON scene.id=es.sceneId
        LEFT JOIN area ON es.areaId=area.id
        LEFT JOIN ap ON es.apId=ap.id
        WHERE
        1=1
        <if test="sceneId==null and areaId==null">
            and scene.name IS NOT NULL
        </if>
        <if test="sceneId!=null and areaId==null">
            and scene.name IS NOT NULL
            and scene.id=#{sceneId}
        </if>
        <if test="areaId!=null and sceneId!=null">
            and area.name IS NOT NULL
            and area.id=#{areaId}
        </if>
    </select>

    <select id="selectGTETData" resultType="com.suzao.net.speed.netspeed.vo.network.ExperienceSpeedVo"
            parameterType="java.util.List">
        SELECT
        es.`id`,
        es.`platform`,
        es.`speed`,
        es.`time`,
        es.`address`,
        es.`macAddress`,
        es.`macAddress5G`,
        es.`sceneId`,
        es.`areaId`,
        es.`apId`,
        es.`speedometer`,
        scene.`name` sceneName,
        area.`name` areaName,
        ap.`name` apName
        FROM
        experiencespeed es
        LEFT JOIN scene ON es.sceneId=scene.id
        LEFT JOIN area ON es.areaId =area.id
        LEFT JOIN ap ON es.apId=ap.id
        WHERE
        1=1
        and
        es.speed <![CDATA[>= ]]>${networkPassValue}
        <if test="sceneName!=null">
            AND scene.name=#{sceneName}
        </if>
        <if test="areaName!=null">
            AND area.name=#{areaName}
        </if>
        <if test="apName!=null">
            AND ap.name=#{apName}
        </if>

    </select>

    <select id="selectLTData" resultType="com.suzao.net.speed.netspeed.vo.network.ExperienceSpeedVo"
            parameterType="java.util.List">
        SELECT
        es.`id`,
        es.`platform`,
        es.`speed`,
        es.`time`,
        es.`address`,
        es.`macAddress`,
        es.`macAddress5G`,
        es.`sceneId`,
        es.`areaId`,
        es.`apId`,
        es.`speedometer`,
        scene.`name` sceneName,
        area.`name` areaName,
        ap.`name` apName
        FROM
        experiencespeed es
        LEFT JOIN scene ON es.sceneId=scene.id
        LEFT JOIN area ON es.areaId =area.id
        LEFT JOIN ap ON es.apId=ap.id
        WHERE
        1=1
        and
        es.speed <![CDATA[< ]]>${networkPassValue}
        <if test="sceneName!=null">
            AND scene.name=#{sceneName}
        </if>
        <if test="areaName!=null">
            AND area.name=#{areaName}
        </if>
        <if test="apName!=null">
            AND ap.name=#{apName}
        </if>

    </select>

    <select id="selectData" resultType="com.suzao.net.speed.netspeed.vo.network.ExperienceSpeedVo"
            parameterType="java.util.List">
        SELECT
        es.`id`,
        es.`platform`,
        es.`speed`,
        es.`time`,
        es.`address`,
        es.`macAddress`,
        es.`macAddress5G`,
        es.`sceneId`,
        es.`areaId`,
        es.`apId`,
        es.`speedometer`,
        scene.`name` sceneName,
        area.`name` areaName,
        ap.`name` apName
        FROM
        experiencespeed es
        LEFT JOIN scene ON es.sceneId=scene.id
        LEFT JOIN area ON es.areaId =area.id
        LEFT JOIN ap ON es.apId=ap.id
        WHERE
        1=1
        <if test="sceneName!=null">
            AND scene.name=#{sceneName}
        </if>
        <if test="areaName!=null">
            AND area.name=#{areaName}
        </if>
        <if test="apName!=null">
            AND ap.name=#{apName}
        </if>

    </select>

</mapper>
